letsearch_client/__init__.py
letsearch_client/export_to_onnx.py
letsearch_client/letsearch_client.py
letsearch_client/types.py
letsearch_client-0.1.1.dist-info/METADATA
letsearch_client-0.1.1.dist-info/WHEEL
letsearch_client-0.1.1.dist-info/entry_points.txt
letsearch_client-0.1.1.dist-info/top_level.txt
letsearch_client-0.1.1.dist-info/RECORD
