Metadata-Version: 2.1
Name: letsearch-client
Version: 0.1.1
Summary: Python client for letsearch, RAG-native vector DB in a single binary to embed, index and serve your documents for search
Author-email: Yusuf Sarıgöz <yusufsarigoz@gmail.com>
Project-URL: homepage, https://github.com/monatis/letsearch
Project-URL: project, https://github.com/monatis/letsearch
Project-URL: repository, https://github.com/monatis/letsearch-client
Keywords: letsearch,rag,vectordb,onnx
Classifier: Intended Audience :: Developers
Classifier: License :: OSI Approved :: MIT License
Classifier: Programming Language :: Python :: 3.10
Classifier: Programming Language :: Python :: 3.11
Classifier: Programming Language :: Python :: 3.12
Classifier: Topic :: Software Development :: Libraries :: Python Modules
Requires-Python: >=3.10
Requires-Dist: httpx>=0.28.1
Requires-Dist: pydantic>=2.10.3
Provides-Extra: conversion
Requires-Dist: torch>=2.5.1; extra == "conversion"
Requires-Dist: torchvision; extra == "conversion"
Requires-Dist: onnx; extra == "conversion"
Requires-Dist: onnxruntime; extra == "conversion"
Requires-Dist: transformers; extra == "conversion"
Requires-Dist: pytest>=8.3.4; extra == "conversion"
